{
  "legacy_node_id": "2950",
  "original_slug": "/activity/festivals-events/blue-friday-and-light-up-blue-ridge",
  "content_body": "<p>A few days after Thanksgiving, <a href=\"https://lightupblueridge.info\">Blue Ridge</a> puts a spin on Black Friday with &quot;Blue Friday,&quot; so visit downtown Blue Ridge for incredible deals in the boutique shops! On Saturday, Blue Ridge will light the massive Christmas tree located in the heart of downtown while surrounded by holiday entertainment, Santa, and more!&nbsp;</p>",
  "category_tags": [],
  "node_type": "activity",
  "body_status": "verified",
  "signed_at": "2026-03-20T16:36:28Z",
  "legacy_type": "page",
  "title": "Blue Friday and Light Up Blue Ridge",
  "archive_slug": "blue-friday-and-light-up-blue-ridge",
  "archive_path": "/reviews/archive/blue-friday-and-light-up-blue-ridge",
  "source_ref": "node/2950",
  "legacy_created_at": 1687967898,
  "legacy_updated_at": 1688136581,
  "legacy_author_id": "13",
  "legacy_language": "und",
  "hmac_signature": "ffe3a4e57753bccf7d98b24d779b5bc29fc5d0e42d5b4c99b1c99e284822ec60"
}