{
  "legacy_node_id": "3092",
  "original_slug": "/activity/fishing/blue-ridge/captn-joes-lake-adventures",
  "content_body": "<p><a href=\"https://captnjoeslakeadventures.com/home\">Capt&#39;n Joe&#39;s Lake Adventures</a> in Blue Ridge, GA, offers an exciting and immersive way to explore the stunning Lake Blue Ridge.</p>\r\n\r\n<p>Specializing in guided boat tours and fishing excursions, Capt&#39;n Joe&#39;s provides a unique opportunity to experience the natural beauty and abundant wildlife of this pristine lake.</p>\r\n\r\n<p>Whether you&#39;re an avid angler looking to catch trophy fish or simply seeking a relaxing day on the water, Capt&#39;n Joe&#39;s has something for everyone.</p>\r\n\r\n<p>The friendly and experienced crew at Capt&#39;n Joe&#39;s is dedicated to providing exceptional service and creating lasting memories for every guest.</p>\r\n\r\n<p>Whether you&#39;re planning a family outing, a romantic getaway, or a fun day with friends, Capt&#39;n Joe&#39;s Lake Adventures promises an unforgettable experience on the beautiful waters of Lake Blue Ridge.</p>",
  "category_tags": [],
  "node_type": "activity",
  "body_status": "verified",
  "signed_at": "2026-03-20T16:35:38Z",
  "legacy_type": "page",
  "title": "Capt'n Joe's Lake Adventures",
  "archive_slug": "captn-joes-lake-adventures",
  "archive_path": "/reviews/archive/captn-joes-lake-adventures",
  "source_ref": "node/3092",
  "legacy_created_at": 1722958919,
  "legacy_updated_at": 1738179206,
  "legacy_author_id": "13",
  "legacy_language": "und",
  "hmac_signature": "e2c0adb7753b9f958e7e1d3ff0c28522a6183d97c7762f69d592efe5aa61809d"
}