{
  "legacy_node_id": "2904",
  "original_slug": "/activity/wineries-vineyards/34th-degree-wine-merchant",
  "content_body": "<p>Visit Blue Ridge&#39;s <strong>first</strong>&nbsp;fully dedicated <a href=\"https://34thdegreewine.com\">wine shop</a>!&nbsp;Looking for wine for everyday enjoyment? Need food pairing recommendations? Planning an order for a special event? Building your cellar collection to enjoy for years to come?</p>\r\n\r\n<p>This team of passionate, friendly, knowledgeable wine specialists will gladly assist you in finding the perfect bottle, no matter the occasion! 34th Degree offers wine tasting, wine classes, and even a wine club to subscribe to.</p>\r\n\r\n<ul>\r\n\t<li><strong>Wine Tasting</strong> - Weekly Wine Tastings</li>\r\n\t<li><strong>Wine Classes</strong> - Join a class on how to imaginatively pair wines with different foods, explore different wine regions from around the globe, enjoy insights from guest speakers, and go on in-depth explorations of different wines based on monthly themes.&nbsp;</li>\r\n\t<li><strong>Wine Club</strong> - Each month, they&#39;ll carefully curate a selection of wines based on variety, seasonality, staff selections, and more to crate an unforgettable assortment of bottles for you to enjoy. You can pick up your win in store, curbside, or join for the monthly Pick Up Party, where you can try different pairings, swap out elect bottles, or upgrade that month&#39;s assortment, all while enjoying the company of the 34th Degree community.</li>\r\n</ul>",
  "category_tags": [],
  "node_type": "activity",
  "body_status": "verified",
  "signed_at": "2026-03-20T16:36:14Z",
  "legacy_type": "page",
  "title": "34th Degree Wine Merchant",
  "archive_slug": "34th-degree-wine-merchant",
  "archive_path": "/reviews/archive/34th-degree-wine-merchant",
  "source_ref": "node/2904",
  "legacy_created_at": 1660772328,
  "legacy_updated_at": 1715619294,
  "legacy_author_id": "12",
  "legacy_language": "und",
  "hmac_signature": "555f2bc04cbe9da4bdd26171e9ac2e7f9c86b6c91ac31a5ac9cd1d4b70ae9a9a"
}