{
  "legacy_node_id": "2620",
  "original_slug": "/activity/restaurants/blue-ridge/roots-organic-juice-bar",
  "content_body": "<p><a href=\"https://www.facebook.com/rootsorganicjuicebar/\">ROOTS</a>&nbsp;Organic Juice Bar,&nbsp;Blue&nbsp;Ridge, Georgia. Fast food can be good food! Stop in and grab some organic, fresh-pressed juices, shakes, and vegan snacks!</p>\r\n\r\n<p>Using fresh fruits and ingredients, Roots is your place for healthy, delicious juices and smoothies using Isagenix products to enhance good health and energy.</p>",
  "category_tags": [],
  "node_type": "activity",
  "body_status": "verified",
  "signed_at": "2026-03-20T16:35:57Z",
  "legacy_type": "page",
  "title": "Roots Organic Juice Bar",
  "archive_slug": "roots-organic-juice-bar",
  "archive_path": "/reviews/archive/roots-organic-juice-bar",
  "source_ref": "node/2620",
  "legacy_created_at": 1597435320,
  "legacy_updated_at": 1719328684,
  "legacy_author_id": "12",
  "legacy_language": "und",
  "hmac_signature": "cb3f4994485841c0b9cc1d1e76b1deb358ca15e4a2f072a4cb9465e03e9f838f"
}