{
  "legacy_node_id": "1478",
  "original_slug": "/testimonial/better-than-we-expected",
  "content_body": "<p>The property was better than we expected. We have been renting properties through VRBO in Georgia, North Carolina, Tennessee and this property was definitely the best. Last summer, we rented a different house in Blue Ridge and we liked the town so much that&nbsp;we decided to come back this year again. We are extremely concerned with cleanliness, but with this house there was not a single issue. Everything was perfect and clean. The view from every room is breathtaking. We stayed with my two kids, which are 18 and 14, and my parents-in-law. It was the best relaxing week. My wife and in-laws are already planning another trip to Blue Ridge again. I highly recommend this property!!!</p>",
  "category_tags": [],
  "node_type": "testimonial",
  "body_status": "verified",
  "signed_at": "2026-03-20T00:44:27Z",
  "title": "Better Than We Expected",
  "archive_slug": "better-than-we-expected",
  "archive_path": "/reviews/archive/better-than-we-expected",
  "source_ref": "node/1478",
  "hmac_signature": "c2d2031c6fcb660b33ed7cafffff63434f9e2046663484e1ff99f633e1cf83dc"
}