{
  "legacy_node_id": "184",
  "original_slug": "/testimonial/great-fellowship-had-all",
  "content_body": "<p>Awesome home, location and view. We had a great time fellowshipping. The fire pit was awesome.</p>",
  "category_tags": [],
  "node_type": "testimonial",
  "body_status": "verified",
  "signed_at": "2026-03-20T00:44:27Z",
  "title": "Great Fellowship had by All",
  "archive_slug": "great-fellowship-had-all",
  "archive_path": "/reviews/archive/great-fellowship-had-all",
  "source_ref": "node/184",
  "hmac_signature": "6b7dc6095efd537a05fd46d2d8429cf987c164ad568d0e92ae4de4df63b8c7f2"
}