{
  "legacy_node_id": "2368",
  "original_slug": "/testimonial/laughs-and-tremendous-fun-had-rolling-river",
  "content_body": "<p>We came here for a girls trip of family and friends. We laughed and had more fun than we&#39;ve had in a long time. This cabin was wonderful. Thank you for the great experience.&nbsp;</p>",
  "category_tags": [
    "Family Fun",
    "Toccoa River"
  ],
  "node_type": "testimonial",
  "body_status": "verified",
  "signed_at": "2026-03-20T00:44:27Z",
  "title": "Laughs and Tremendous Fun Had At Rolling River",
  "archive_slug": "laughs-and-tremendous-fun-had-rolling-river",
  "archive_path": "/reviews/archive/laughs-and-tremendous-fun-had-rolling-river",
  "source_ref": "node/2368",
  "related_property_slug": "rolling-river-cabin",
  "related_property_path": "/cabins/rolling-river-cabin",
  "related_property_title": "A Rolling River Cabin",
  "hmac_signature": "f6f35d6403ba61af2e5203ebd10db6dd53bcec011ce2b9bea85f220354095c6a"
}