{
  "legacy_node_id": "1249",
  "original_slug": "/testimonial/looking-forward-to-visiting-again",
  "content_body": "<p>My husband and I just returned from the Outlaw Ridge cabin for a couples&rsquo; retreat. We enjoyed everything from the clean and spacious rooms to the relaxing and peaceful views. Being there really gave us some much needed quality time. The only thing was regret is not staying an extra night. We were very pleased with our stay at your cabin, and we&rsquo;re looking forward to visiting again.</p>",
  "category_tags": [],
  "node_type": "testimonial",
  "body_status": "verified",
  "signed_at": "2026-03-20T00:44:27Z",
  "title": "Looking Forward to Visiting Again",
  "archive_slug": "looking-forward-to-visiting-again",
  "archive_path": "/reviews/archive/looking-forward-to-visiting-again",
  "source_ref": "node/1249",
  "hmac_signature": "2a554b419436fdc3014303aab06d2c91aab09b2af60f28ab0f3473fe17072467"
}