{
  "legacy_node_id": "2032",
  "original_slug": "/testimonial/only-regret-was-that-we-could-not-stay-longer",
  "content_body": "<p>My wife and I traveled to Blue Ridge for our 25th anniversary. We chose the Mayfly Lodge due to it being a newer cabin with easy access. The cabin is great. The more we looked around, the more we were impressed by the craftsmanship of the cabin. The furnishings are comfortable and the cabin was very clean. Only regret was that we could not stay longer.</p>",
  "category_tags": [],
  "node_type": "testimonial",
  "body_status": "verified",
  "signed_at": "2026-03-20T00:44:27Z",
  "title": "\"Only regret was that we could not stay longer.\"",
  "archive_slug": "only-regret-was-that-we-could-not-stay-longer",
  "archive_path": "/reviews/archive/only-regret-was-that-we-could-not-stay-longer",
  "source_ref": "node/2032",
  "hmac_signature": "7a8aeba9c0bc8fc0f2cb0ce6840d381b20acf223d9d8c409d2aadded08e77771"
}