{
  "legacy_node_id": "2281",
  "original_slug": "/testimonial/our-third-time-here",
  "content_body": "<p>We had a blast! This is our third time renting this cabin, needless to say it&#39;s one of our favs! We had two college grads we are celebrating and this is where they wanted to come. We made such fond memories. Thank you so much for sharing your lovely getaway. We really enjoyed it again!</p>",
  "category_tags": [],
  "node_type": "testimonial",
  "body_status": "verified",
  "signed_at": "2026-03-20T00:44:27Z",
  "title": "Our Third Time Here!",
  "archive_slug": "our-third-time-here",
  "archive_path": "/reviews/archive/our-third-time-here",
  "source_ref": "node/2281",
  "hmac_signature": "91e68e72394df69802473ca90cccd967e15f28893b08a49a80339449002100e9"
}