{
  "legacy_node_id": "913",
  "original_slug": "/testimonial/out-this-world",
  "content_body": "<p>What a cabin, lots of space, rooms and beds are just out of this world. Thanks for a great stay. More than a five star. Looking forward to staying again next year.</p>",
  "category_tags": [],
  "node_type": "testimonial",
  "body_status": "verified",
  "signed_at": "2026-03-20T00:44:27Z",
  "title": "Out of This World!",
  "archive_slug": "out-this-world",
  "archive_path": "/reviews/archive/out-this-world",
  "source_ref": "node/913",
  "hmac_signature": "f9876bc0e3a15c0f769f6e1730285bd6b098a533192c6fe8c7d84d45f60084d4"
}