{
  "legacy_node_id": "2608",
  "original_slug": "/testimonial/perfect-6",
  "content_body": "<p>This property was PERFECT! I would recommend everyone to stay at this cabin home. The bed was comfortable the kitchen had everything to accommodate whatever we needed. The jacuzzi in the balcony was so relaxing and the view made it just 1000 times better.</p>",
  "category_tags": [],
  "node_type": "testimonial",
  "body_status": "verified",
  "signed_at": "2026-03-20T00:44:28Z",
  "title": "Perfect!",
  "archive_slug": "perfect-6",
  "archive_path": "/reviews/archive/perfect-6",
  "source_ref": "node/2608",
  "hmac_signature": "d4fd88922c076112d7e108ad8df4b52ff8646a43a5e44dcbbc4ad738b6c8bc78"
}