{
  "legacy_node_id": "189",
  "original_slug": "/testimonial/quick-getaway-to-the-north-georgia-mountains",
  "content_body": "<p>We drove up from Florida for a quick getaway in the mountains. The cabin was amazing. It was so nicely tucked away in the mountains that you felt like you had left the rest of the world behind. Celtic Clouds was a perfect choice for us, and we can&#39;t wait to come back again!</p>",
  "category_tags": [
    "North Carolina"
  ],
  "node_type": "testimonial",
  "body_status": "verified",
  "signed_at": "2026-03-20T00:44:27Z",
  "title": "A Quick Getaway to the North Georgia Mountains",
  "archive_slug": "quick-getaway-to-the-north-georgia-mountains",
  "archive_path": "/reviews/archive/quick-getaway-to-the-north-georgia-mountains",
  "source_ref": "node/189",
  "hmac_signature": "11a6954827f47422ceb793bcc655c0820990d11ca7f758e0b6037c17ea98a6ba"
}