{
  "legacy_node_id": "204",
  "original_slug": "/testimonial/relaxation-adventures-happen-fallen-timber-lodge",
  "content_body": "<p>What a fabulous getaway we&#39;ve had! This home is simply perfect and we feel blessed to have spent 4 relaxing, adventurous, fun, cozy, peaceful days here. The view is mesmerizing and we often caught ourselves just staring, lost in thought (Like, &quot;Do I really have to go home&quot;). We ventured out and walked the train tracks, we did some fly fishing (well actually a lot of Fly Fishing), Robert pulled out a fish the size of a golden retriever...unfortunately it got away before we could take a picture. The train is charming and we enjoyed waving to the passengers as they rolled by. The only way to have made our stay better - would be to extend it! We look forward to returning again and again.</p>",
  "category_tags": [
    "Fall"
  ],
  "node_type": "testimonial",
  "body_status": "verified",
  "signed_at": "2026-03-20T00:44:27Z",
  "title": "Relaxation & Adventures Happen at Fallen Timber Lodge",
  "archive_slug": "relaxation-adventures-happen-fallen-timber-lodge",
  "archive_path": "/reviews/archive/relaxation-adventures-happen-fallen-timber-lodge",
  "source_ref": "node/204",
  "related_property_slug": "fallen-timber-lodge",
  "related_property_path": "/cabins/fallen-timber-lodge",
  "related_property_title": "Fallen Timber Lodge",
  "hmac_signature": "6316816784fececb2ce10ecbac725f791fcda04b8920ba1196842e4335b6b6ef"
}