{
  "legacy_node_id": "2376",
  "original_slug": "/testimonial/spectacular-peaceful-and-beautiful",
  "content_body": "<p>Thank you for offering such a peaceful and beautiful place for common folks to come and call this home for a couple of days. What a spectacular view!&nbsp;</p>",
  "category_tags": [],
  "node_type": "testimonial",
  "body_status": "verified",
  "signed_at": "2026-03-20T00:44:27Z",
  "title": "Spectacular, Peaceful, and Beautiful",
  "archive_slug": "spectacular-peaceful-and-beautiful",
  "archive_path": "/reviews/archive/spectacular-peaceful-and-beautiful",
  "source_ref": "node/2376",
  "hmac_signature": "79444ad95ed0918ff6222ad9ef7568d27fc0b2afb540a570c157d556386e62aa"
}