{
  "legacy_node_id": "2004",
  "original_slug": "/testimonial/this-cabin-touched-our-hearts",
  "content_body": "<p>What a great cabin to come to and get away from our busy lives. Sometimes amidst the crazy lives, yet wonderful, that God has given us, we forget what comfort our families bring to us! Being in this cabin throughout these days, we have enjoyed, laughed, and have remembered what our family has achieved in our 16 years of marriage. On a different note, we caught our first carp and enjoyed every minute of it! We only hope that this cabin touches the heart of others as it did for us. ~The Dominguez Family</p>",
  "category_tags": [],
  "node_type": "testimonial",
  "body_status": "verified",
  "signed_at": "2026-03-20T00:44:27Z",
  "title": "This Cabin Touched Our Hearts!",
  "archive_slug": "this-cabin-touched-our-hearts",
  "archive_path": "/reviews/archive/this-cabin-touched-our-hearts",
  "source_ref": "node/2004",
  "related_property_slug": "our-true-blue",
  "related_property_path": "/cabins/our-true-blue",
  "related_property_title": "Our True Blue",
  "hmac_signature": "324f622f9260dd1c180a3d4d9d9f8d80c63938a779e55306852a17fa26140367"
}