{
  "legacy_node_id": "1992",
  "original_slug": "/testimonial/we-enjoyed-our-thanksgiving-here",
  "content_body": "<p>We enjoyed our Thanksgiving stay here in the cabin in Murphy. Great house, beautiful views, and great family time. Very relaxing. ~Memphis, TN</p>",
  "category_tags": [],
  "node_type": "testimonial",
  "body_status": "verified",
  "signed_at": "2026-03-20T00:44:27Z",
  "title": "We Enjoyed Our Thanksgiving Here!",
  "archive_slug": "we-enjoyed-our-thanksgiving-here",
  "archive_path": "/reviews/archive/we-enjoyed-our-thanksgiving-here",
  "source_ref": "node/1992",
  "hmac_signature": "056f6a8706a1225b26672abc736ef20c0857f98440ab1890faccca465f96b0de"
}