{
  "legacy_node_id": "2176",
  "original_slug": "/testimonial/we-will-spread-the-word",
  "content_body": "<p>This cabin is amazing! The view is beautiful from all angles, the amenities are handy and fun, and the sound of the river winding by is sooo relaxing. It is the perfect spot for any getaway! We enjoyed the property immensely, and will spread the word about Down By The River! Thank you, Friends, Inc. Couples Trip 2018</p>\r\n\r\n<p>&nbsp;</p>",
  "category_tags": [],
  "node_type": "testimonial",
  "body_status": "verified",
  "signed_at": "2026-03-20T00:44:27Z",
  "title": "We Will Spread The Word!",
  "archive_slug": "we-will-spread-the-word",
  "archive_path": "/reviews/archive/we-will-spread-the-word",
  "source_ref": "node/2176",
  "hmac_signature": "d285b80c8595e3c42f3ddeaa4a5c74bdd25977de5551f23de09ad623b15b76fb"
}