{
  "legacy_node_id": "2175",
  "original_slug": "/testimonial/we-will-definitely-do-this-again",
  "content_body": "<p>This was a great couples retreat! &nbsp;The cabin was perfectly warm and inviting. We relaxed, watched movies, and really enjoyed the piano room that we renamed the Boom Boom Room! :) We chilled in the hot tub, and loved the kitchen as well. There wre great meals prepared and enjoyed. We will definitely do this again!! Thank you Mayfly Lodge! ~ Love, the Davids and Riley&#39;s</p>\r\n\r\n<p>&nbsp;</p>",
  "category_tags": [],
  "node_type": "testimonial",
  "body_status": "verified",
  "signed_at": "2026-03-20T00:44:27Z",
  "title": "We will definitely do this again!",
  "archive_slug": "we-will-definitely-do-this-again",
  "archive_path": "/reviews/archive/we-will-definitely-do-this-again",
  "source_ref": "node/2175",
  "hmac_signature": "3b991b81a1521198f4843eca2295128b0349e652d29f3a881d140f9652b80293"
}