{
  "legacy_node_id": "3220",
  "original_slug": "/testimonial/wonderful-stay-spent-exploring",
  "content_body": "<p>Had an awesome time.&nbsp;We went to Vogel Falls, Dahlonega to have lunch and do a little shopping. Then we went to Dawsonville for breakfast and more shopping. On our last day, we&#39;re going to hike to The Swinging Bridge. Saw deer on the side yard this morning. So cool! We enjoyed evenings by the fire, fishing, shopping, exploring, walks, and hiking. Beautiful location for a cabin. Very serene! Thank you!&nbsp;</p>",
  "category_tags": [],
  "node_type": "testimonial",
  "body_status": "verified",
  "signed_at": "2026-03-20T00:44:28Z",
  "title": "Wonderful Stay Spent Exploring",
  "archive_slug": "wonderful-stay-spent-exploring",
  "archive_path": "/reviews/archive/wonderful-stay-spent-exploring",
  "source_ref": "node/3220",
  "hmac_signature": "c673289ec298d5c43d5d84ba1292d0ef0ab28f191d35562fad11ae379830a578"
}