{
  "legacy_node_id": "2983",
  "original_slug": "/activity/waterfalls/jacks-river-falls",
  "content_body": "<p>Located in the Cohutta Wilderness Area on the Jacks River, this beautiful waterfall is the most visited site in the Cohutta and is reached by a 4.5-mile trail through rugged wilderness.</p>\r\n\r\n<p>After heavy rainfall, the falls transform into a powerful whitewater cascade, plunging 80 feet into the valley below. In contrast, during the hot, dry summer months, the falls showcase their striking rock formations and provide more tranquil swimming holes rather than roaring torrents.</p>\r\n\r\n<p>The falls are slightly past the halfway point if the trail is hiked from end to end. A great place to take an extended lunch break and swim in warm weather.</p>\r\n\r\n<p>&nbsp;</p>\r\n\r\n<p>&nbsp;</p>",
  "category_tags": [],
  "node_type": "activity",
  "body_status": "verified",
  "signed_at": "2026-03-20T16:36:03Z",
  "legacy_type": "page",
  "title": "Jacks River Falls",
  "archive_slug": "jacks-river-falls",
  "archive_path": "/reviews/archive/jacks-river-falls",
  "source_ref": "node/2983",
  "legacy_created_at": 1692120449,
  "legacy_updated_at": 1737763505,
  "legacy_author_id": "13",
  "legacy_language": "und",
  "hmac_signature": "ec3d484182189539b9fb43793d66465251cfde0f5a29858004e435444df84afc"
}