{
  "legacy_node_id": "2109",
  "original_slug": "/activity/restaurants/blue-ridge/harvest-main",
  "content_body": "<p>With a nationally recognized chef at the helm, <a href=\"http://harvestonmain.com/\">Harvest On Main</a>&#39;s&nbsp;mission is to serve the best quality ingredients they can find. Their menu is globally influenced by a southern twang, and proud of local farmers and suppliers. They use seasonal products whenever possible, supporting our local economy, farmers, and artisans.&nbsp;Producers include our own production from The Cook&rsquo;s Farm, Logan Turnpike Mill, Mercier Orchards, Brasstown Beef, Bramlett Trout Farm, Foster&rsquo;s Produce, The Chef&rsquo;s Garden, and other small local producers.&nbsp;</p>",
  "category_tags": [],
  "node_type": "activity",
  "body_status": "verified",
  "signed_at": "2026-03-20T16:35:44Z",
  "legacy_type": "page",
  "title": "Harvest On Main",
  "archive_slug": "harvest-main",
  "archive_path": "/reviews/archive/harvest-main",
  "source_ref": "node/2109",
  "legacy_created_at": 1500488296,
  "legacy_updated_at": 1717683483,
  "legacy_author_id": "13",
  "legacy_language": "und",
  "hmac_signature": "59ee1a7fe1adf76107e766fc4976add594088a2d08b570b9c6542deb9b57affe"
}