{
  "legacy_node_id": "946",
  "original_slug": "/blog/2014/07/17/5-reasons-to-reconnect-with-nature",
  "content_body": "<p>Anyone can vouch for the soothing, rejuvenating effect that seems to come with the great outdoors. There&rsquo;s just something about breathing in the fresh scent of evergreen trees, listening to trickling water, and watching the sky transform into a gorgeous color palette at&nbsp;sunset that makes your brain go&nbsp;<em>ahh</em>. But did you know that spending time in nature offers considerable&nbsp;benefits to&nbsp;your mind and body?&nbsp;As if the sheer beauty of luscious green forests&nbsp;and snow-capped mountain landscapes&nbsp;wasn&rsquo;t enough to inspire you to book your next nature retreat, here are five reasons that you should make plans to reconnect with Mother Nature.</p>\r\n\r\n<p>&nbsp;</p>\r\n\r\n<p><strong>1.&nbsp;</strong><strong>It makes you happy.</strong></p>\r\n\r\n<p>More and more studies are showing that being outside&nbsp;in nature elicits happiness. Even a simple look at a natural scene can produce this effect. In fact,&nbsp;<a href=\"http://www.ncbi.nlm.nih.gov/pmc/articles/PMC2930158\">a study done at Chonnam National University in South Korea</a>&nbsp;found that images of landscapes, such as forests and mountains, heightened activity in the areas of the brain linked to emotional stability, positive outlook, and happy memories.</p>\r\n\r\n<p>&nbsp;</p>\r\n\r\n<p><strong>2.&nbsp;</strong><strong>It makes you healthy.</strong></p>\r\n\r\n<p>Researchers have also linked more time in nature with both physical and emotional health benefits. They&#39;ve found that being outside reduces stress, lowers blood pressure, combats depression, and even leads to faster healing time. Additionally,&nbsp;a Japanese study&nbsp;found that spending time in a forest environment had beneficial effects on insulin sensitivity and blood glucose levels in patients with Type 2 Diabetes.</p>\r\n\r\n<p>&nbsp;</p>\r\n\r\n<p><strong>3.&nbsp;</strong><strong>It makes you more focused.</strong></p>\r\n\r\n<p>We all know hanging out with Mother Nature&nbsp;gives our brains a break from the hustle and bustle of everyday life, but it can also&nbsp;help&nbsp;increase your focus once you get back to the daily grind.&nbsp;Researchers at the University of Michigan&nbsp;concluded that just an hour spent interacting with nature improved attention span, as well as memory performance. Both increased by 20 percent in their&nbsp;2008 study.</p>\r\n\r\n<p>&nbsp;</p>\r\n\r\n<p><strong>4.&nbsp;</strong><strong>It makes you nicer.</strong></p>\r\n\r\n<p>Having trouble relating to others? Turns out scientists have demonstrated that spending time in nature leads to increases in empathy.&nbsp;A&nbsp;study done at the University of Rochester&nbsp;found that when people were exposed to natural environments, they placed a higher value on community and close relationships. They were even more generous with money. The more subjects engaged with the natural settings, the more pronounced these effects became.</p>\r\n\r\n<p>&nbsp;</p>\r\n\r\n<p><strong>5.&nbsp;</strong><strong>It makes you more creative.</strong></p>\r\n\r\n<p>If you can find the strength to step away from the internet, put down your cell phone, pack up that iPad, and head outside, you&rsquo;ll find that it&rsquo;s not just good for your mental health; it&rsquo;s also good for your inner artist. Researchers at the University of Kansas reported that people who were immersed in nature and disconnected from electronics for a few days saw a boost in creativity of almost 50 percent!&nbsp;This&nbsp;2012 study&nbsp;suggests that improvements to creative problem-solving skills&nbsp;peak&nbsp;after about three days of disconnecting from technology and embracing the great outdoors.</p>\r\n\r\n<p>&nbsp;</p>\r\n\r\n<p>So...long weekend in the mountains, anyone?</p>\r\n\r\n<p>&nbsp;</p>",
  "category_tags": [],
  "node_type": "blog",
  "body_status": "verified",
  "signed_at": "2026-03-20T16:34:40Z",
  "legacy_type": "blog_post",
  "title": "5 Reasons to Reconnect with Nature",
  "archive_slug": "5-reasons-to-reconnect-with-nature",
  "archive_path": "/reviews/archive/5-reasons-to-reconnect-with-nature",
  "source_ref": "node/946",
  "legacy_created_at": 1405606375,
  "legacy_updated_at": 1741012037,
  "legacy_author_id": "4",
  "legacy_language": "und",
  "hmac_signature": "0a9e044797a18e94fc13c78f619c0d83f4d677a27bf4bb48fdded120239b3b0b"
}