{
  "legacy_node_id": "994",
  "original_slug": "/riverfront-cabins",
  "content_body": "<p><em>&quot;Time is like a river. You cannot touch the same water twice, because&nbsp;the flow that has passed will never pass again. Enjoy every moment of your life.&quot;&nbsp;</em></p>\r\n\r\n<h2><em>Luxury Vacation Rentals in Blue Ridge GA</em></h2>\r\n\r\n<p>There is a special place in Blue Ridge, Georgia where the living is grand,&nbsp;the beauty is unsurpassed, and your spirit is refreshed. Over the years,&nbsp;Cabin Rentals of Georgia has selectively chosen luxury homes offering river frontage and river view&nbsp;cabins&nbsp;that soothe and delight. Experience a cabin trip in Georgia and make some memories.</p>\r\n\r\n<p>If you are looking for a getaway that will refresh and rejuvenate your senses, our riverfront&nbsp;luxury cabins in Georgia will be sure to melt away the cares of this world, enabling you to&nbsp;enjoy every moment of your life. To feel the earth under your&nbsp;feet, to revel in&nbsp;the river rushing&nbsp;through your fingers, to experience the flow of the seasons, to smell the fresh mountain air of a new morning and to be awed by the peaceful, starry skies at night...this encapsulates the Blue Ridge Experience.&nbsp;&nbsp;</p>\r\n\r\n<p>Inspired by the natural beauty that embraces each and every corner, you will be immersed into a sophisticated river/mountain experience with the perfect blend of mountain lodge architecture and rustic elegance.</p>\r\n\r\n<h2><em>Aska Adventure Area River Cabins</em></h2>\r\n\r\n<p>Enjoy&nbsp;luxurious riverfront cabins in Georgia, some featuring spacious outdoor living spaces with fireplaces, while others offer open floor plans with spacious kitchens and big views of the Blue Ridge Mountains and the Toccoa River.&nbsp;In the reputable Aska Adventure Area, several&nbsp;beautiful luxury cabins can be found perched high on a ridge overlooking the Toccoa River in the very heart of the Aska Adventure Area or near the Toccoa River and hiking trails - where everything is at the thrill-seeker&#39;s fingertips - from hiking and&nbsp;kayaking, to mountain biking and gem mining.&nbsp;</p>\r\n\r\n<h2><em>Toccoa River Activities From Your Cabin Rental</em></h2>\r\n\r\n<p>The Toccoa River is the main river running through Blue Ridge and feeds into Lake Blue Ridge.&nbsp; We have a couple of 5-bedroom luxury cabin rentals along the Toccoa River which offers over 1,000 feet of river frontage. &nbsp;</p>\r\n\r\n<h3><em>Georgia Trout Fishing</em></h3>\r\n\r\n<p>When not inside basking in the expansive views of the mountains and river, venture outdoors and find a path down to the river where you can enjoy fantastic trout fishing&nbsp;as the Cherokee Indians built one of their beautiful fish traps&nbsp;seen and used to great benefit right from our property.</p>\r\n\r\n<h3><em>Tubing and Whitewater Rafting</em></h3>\r\n\r\n<p>Put in a tube, canoe, or kayak and float northwards into the twin towns of McCaysville, GA/Copperhill, TN just a short 10 minute drive from the cabins. Once the river flows there, it becomes the Ocoee River in Tennessee. If adventure and excitement are the theme for the day, you are only 20-30 &nbsp;minutes away from experiencing the thrill of Class III-IV rapids at&nbsp;the Ocoee Whitewater Center. Riverfront cabins create beautiful memories for our guests as they immerse themselves in the beauty of North Georgia.</p>\r\n\r\n<p>As one of our guests stated, &quot;<em>this part of the country is a beautiful canvas to paint life&#39;s most treasured times upon.</em>&quot;</p>",
  "category_tags": [],
  "node_type": "landing_page",
  "body_status": "verified",
  "signed_at": "2026-03-21T11:41:00Z",
  "legacy_type": "page",
  "title": "Riverfront Cabins",
  "archive_slug": "riverfront-cabins",
  "archive_path": "/reviews/archive/riverfront-cabins",
  "source_ref": "node/994",
  "legacy_created_at": 1409198313,
  "legacy_updated_at": 1707860518,
  "legacy_author_id": "5046",
  "legacy_language": "und",
  "hmac_signature": "041870c5dc2bd48ad9f2f8e375c577325aee46e31dece4f80f66980db1acf8fb"
}