{
  "legacy_node_id": "1547",
  "original_slug": "/testimonial/amazing-3",
  "content_body": "<p>One word truly expresses our stay at Cohutta Sunset: AMAZING! Thank you for sharing your beautiful home!</p>",
  "category_tags": [],
  "node_type": "testimonial",
  "body_status": "verified",
  "signed_at": "2026-03-20T00:44:27Z",
  "title": "AMAZING!",
  "archive_slug": "amazing-3",
  "archive_path": "/reviews/archive/amazing-3",
  "source_ref": "node/1547",
  "hmac_signature": "70223ca6c081d14f1960f9680dc8c81560781840454d66e129ad5a8b2bad09bf"
}