{
  "legacy_node_id": "3141",
  "original_slug": "/testimonial/best-weekend-ever",
  "content_body": "<p>The cabin was better than expected, I&rsquo;m kind of a clean freak and I was super impressed. I love the fireplaces. I love the rusticness. I love the waterfall shower in the master bedroom. The swinging bed was just a topper.</p>",
  "category_tags": [],
  "node_type": "testimonial",
  "body_status": "verified",
  "signed_at": "2026-03-20T00:44:28Z",
  "title": "Best Weekend Ever!",
  "archive_slug": "best-weekend-ever",
  "archive_path": "/reviews/archive/best-weekend-ever",
  "source_ref": "node/3141",
  "hmac_signature": "eefbb2cc1957d6968a064888cfc6e594f8cc97c82e5cd085b6ca918cebfda600"
}