{
  "legacy_node_id": "243",
  "original_slug": "/testimonial/birthday-celebration-luxury-lake-blue-ridge-cabin",
  "content_body": "<p>Absolutely Beautiful. We celebrated my 43rd birthday with friends and it was an amazing Do Nothing Good Time. This cabin is beautiful!!! The weather was perfect - just enough chill. Thank you for sharing you home, we had a wonderful time - cooking, drinking and enjoying our friends.</p>",
  "category_tags": [
    "Blue Ridge",
    "Blue Ridge Things To Do",
    "Lake Blue Ridge"
  ],
  "node_type": "testimonial",
  "body_status": "verified",
  "signed_at": "2026-03-20T00:44:27Z",
  "title": "Birthday Celebration at a Luxury Lake Blue Ridge Cabin",
  "archive_slug": "birthday-celebration-luxury-lake-blue-ridge-cabin",
  "archive_path": "/reviews/archive/birthday-celebration-luxury-lake-blue-ridge-cabin",
  "source_ref": "node/243",
  "related_property_slug": "blue-ridge-lake-retreat",
  "related_property_path": "/cabins/blue-ridge-lake-retreat",
  "related_property_title": "Blue Ridge Lake Retreat",
  "hmac_signature": "999537f1ab92d032d448f1b84f09903044100749da5f40c04980bac084f2a556"
}