{
  "legacy_node_id": "1461",
  "original_slug": "/testimonial/looking-forward-to-our-next-stay",
  "content_body": "<p>We had a wonderful stay, from the moment we arrived to the classical music playing for us in the cabin to the time we left. To wake each morning to coffee by the creek was amazing. The cabin itself is beautiful. Loved the hot tub and billiards area. The fire pit and fireplace were great also. After fun days zip lining and whitewater rafting it was nice to return to the cabin and relax. Looking forward to our next stay!</p>",
  "category_tags": [],
  "node_type": "testimonial",
  "body_status": "verified",
  "signed_at": "2026-03-20T00:44:27Z",
  "title": "\"Looking forward to our next stay!\"",
  "archive_slug": "looking-forward-to-our-next-stay",
  "archive_path": "/reviews/archive/looking-forward-to-our-next-stay",
  "source_ref": "node/1461",
  "hmac_signature": "257a811615d8e9a604485567db5483f666fbad5cc6857788daef39357650b7b0"
}