{
  "legacy_node_id": "2001",
  "original_slug": "/testimonial/paradise-the-river",
  "content_body": "<p>Paradise on the river: fishing, swimming, relaxing. Can&#39;t wait to come back! ~The Goldman Family</p>",
  "category_tags": [
    "Toccoa River"
  ],
  "node_type": "testimonial",
  "body_status": "verified",
  "signed_at": "2026-03-20T00:44:27Z",
  "title": "Paradise on the River",
  "archive_slug": "paradise-the-river",
  "archive_path": "/reviews/archive/paradise-the-river",
  "source_ref": "node/2001",
  "hmac_signature": "190db7576eb99a8fab181b4ac17f273e43eefff67ff17664699eba88cf93601a"
}