{
  "legacy_node_id": "1678",
  "original_slug": "/testimonial/thank-you-0",
  "content_body": "<p>Great views from wonderful back porch. Loved sitting and having fires in March! Sad we didn&#39;t catch fish, however, not for lack of trying. Good luck to the next guys. Thank you!</p>",
  "category_tags": [],
  "node_type": "testimonial",
  "body_status": "verified",
  "signed_at": "2026-03-20T00:44:27Z",
  "title": "Thank You!",
  "archive_slug": "thank-you-0",
  "archive_path": "/reviews/archive/thank-you-0",
  "source_ref": "node/1678",
  "hmac_signature": "e179d4d57c43a06acf2ee22021260ea2e496dd578b0a6d66128c6dfdd1ba0d62"
}