{
  "legacy_node_id": "1868",
  "original_slug": "/testimonial/very-relaxing-0",
  "content_body": "<p>Had a great time!! Very relaxing. The cabin was comfortable and well equipped. Enjoyed the trail down to the river. We also went hiking at Fall Branch Falls. Very scenic.&nbsp;</p>\r\n\r\n<p>We had two families and we were all comfortable and enjoyed the cabin very much!&nbsp;</p>",
  "category_tags": [],
  "node_type": "testimonial",
  "body_status": "verified",
  "signed_at": "2026-03-20T00:44:27Z",
  "title": "Very Relaxing...",
  "archive_slug": "very-relaxing-0",
  "archive_path": "/reviews/archive/very-relaxing-0",
  "source_ref": "node/1868",
  "hmac_signature": "238e318d17081f14cafc70213a0f81d685108bc672c06ab868b1c628a0baf537"
}