{
  "legacy_node_id": "1574",
  "original_slug": "/testimonial/we-will-be-back-soon",
  "content_body": "<p>First and foremost, thanks. We had such an amazing time together. Our kids enjoyed everything about the cabin. We will be back soon!</p>",
  "category_tags": [],
  "node_type": "testimonial",
  "body_status": "verified",
  "signed_at": "2026-03-20T00:44:27Z",
  "title": "We Will Be Back Soon!",
  "archive_slug": "we-will-be-back-soon",
  "archive_path": "/reviews/archive/we-will-be-back-soon",
  "source_ref": "node/1574",
  "hmac_signature": "a9886d34231850aeee13f9138d38dd2058b3600dc5ee5cc7d016e129a456e4e0"
}